lab_black.py
nb_black.py
nb_black_formatter-1.0.0.dist-info/LICENSE
nb_black_formatter-1.0.0.dist-info/METADATA
nb_black_formatter-1.0.0.dist-info/WHEEL
nb_black_formatter-1.0.0.dist-info/top_level.txt
nb_black_formatter-1.0.0.dist-info/RECORD
