Metadata-Version: 2.1
Name: nb_black_formatter
Version: 1.0.0
Summary: A simple extension for Jupyter Notebook and Jupyter Lab to beautify Python code automatically using Black.
Home-page: https://github.com/dnanhkhoa/nb_black
Author: Khoa Duong
Author-email: dnanhkhoa@live.com
License: MIT
Keywords: black-formatter black-beautifier black jupyterlab-extension jupyter-notebook-extension
Classifier: Development Status :: 5 - Production/Stable
Classifier: Intended Audience :: Developers
Classifier: License :: OSI Approved :: MIT License
Classifier: Programming Language :: Python
Classifier: Programming Language :: Python :: 3
Classifier: Topic :: Software Development :: Libraries :: Python Modules
License-File: LICENSE
Requires-Dist: ipython
Requires-Dist: yapf >=0.28 ; python_version >= "3.6"
Requires-Dist: black >=23.9 ; python_version >= "3.6"
